{
    "keep": {
        "days": true,
        "amount": 14
    },
    "auditLog": "D:\\Github\\Emp_Portal_BackEnd\\logs\\.c8917d6cb391dcb20f3a3e88de90f9227186fce7-audit.json",
    "files": [
        {
            "date": 1779997173764,
            "name": "D:\\Github\\Emp_Portal_BackEnd\\logs\\request-2026-05-29.log",
            "hash": "6dd6dce6cec79d2c9bf488922ddde0d165b5636eff0a1047bc06292365849c6d"
        },
        {
            "date": 1780127442994,
            "name": "D:\\Github\\Emp_Portal_BackEnd\\logs\\request-2026-05-30.log",
            "hash": "11c6a891ad003ab5f31dc5732fea0da2d4d26a3e8cc7b0f6b268080938986716"
        },
        {
            "date": 1780292018127,
            "name": "D:\\Github\\Emp_Portal_BackEnd\\logs\\request-2026-06-01.log",
            "hash": "71703257d83d572aeae7acb420ed865050049a9d50cc86ce41e068d95e342307"
        },
        {
            "date": 1780478975508,
            "name": "D:\\Github\\Emp_Portal_BackEnd\\logs\\request-2026-06-03.log",
            "hash": "54f2fa21eecbb9afa31ebd8a9a6d78b452411eadc0fa65eb615a2bfc0c72595f"
        },
        {
            "date": 1780562502340,
            "name": "D:\\Github\\Emp_Portal_BackEnd\\logs\\request-2026-06-04.log",
            "hash": "cf48cd0e2f0246c1bcd3a2b4340ace26a77dcd211b9ad733dc8a622c9cd1effa"
        },
        {
            "date": 1780642455470,
            "name": "D:\\Github\\Emp_Portal_BackEnd\\logs\\request-2026-06-05.log",
            "hash": "b4aa8df1bf89b05ba7b8d3b091523a54b1db4155eaa64f68a222ab8a4b24f5a8"
        },
        {
            "date": 1780823530516,
            "name": "D:\\Github\\Emp_Portal_BackEnd\\logs\\request-2026-06-07.log",
            "hash": "c2e8548c17787a96d5c7413da89d70e08708ee58f2ca62f17f710c4e94b6f613"
        }
    ],
    "hashType": "sha256"
}